mutagen/__init__.py
mutagen/_constants.py
mutagen/_file.py
mutagen/_iff.py
mutagen/_riff.py
mutagen/_tags.py
mutagen/_util.py
mutagen/_vorbis.py
mutagen/aac.py
mutagen/ac3.py
mutagen/aiff.py
mutagen/apev2.py
mutagen/dsdiff.py
mutagen/dsf.py
mutagen/easyid3.py
mutagen/easymp4.py
mutagen/flac.py
mutagen/m4a.py
mutagen/monkeysaudio.py
mutagen/musepack.py
mutagen/ogg.py
mutagen/oggflac.py
mutagen/oggopus.py
mutagen/oggspeex.py
mutagen/oggtheora.py
mutagen/oggvorbis.py
mutagen/optimfrog.py
mutagen/smf.py
mutagen/tak.py
mutagen/trueaudio.py
mutagen/wave.py
mutagen/wavpack.py
mutagen/_senf/__init__.py
mutagen/_senf/_argv.py
mutagen/_senf/_compat.py
mutagen/_senf/_environ.py
mutagen/_senf/_fsnative.py
mutagen/_senf/_print.py
mutagen/_senf/_stdlib.py
mutagen/_senf/_temp.py
mutagen/_senf/_winansi.py
mutagen/_senf/_winapi.py
mutagen/_tools/__init__.py
mutagen/_tools/_util.py
mutagen/_tools/mid3cp.py
mutagen/_tools/mid3iconv.py
mutagen/_tools/mid3v2.py
mutagen/_tools/moggsplit.py
mutagen/_tools/mutagen_inspect.py
mutagen/_tools/mutagen_pony.py
mutagen/asf/__init__.py
mutagen/asf/_attrs.py
mutagen/asf/_objects.py
mutagen/asf/_util.py
mutagen/id3/__init__.py
mutagen/id3/_file.py
mutagen/id3/_frames.py
mutagen/id3/_id3v1.py
mutagen/id3/_specs.py
mutagen/id3/_tags.py
mutagen/id3/_util.py
mutagen/mp3/__init__.py
mutagen/mp3/_util.py
mutagen/mp4/__init__.py
mutagen/mp4/_as_entry.py
mutagen/mp4/_atom.py
mutagen/mp4/_util.py
mutagen-1.45.0.data/data/share/man/man1/mid3cp.1
mutagen-1.45.0.data/data/share/man/man1/mid3iconv.1
mutagen-1.45.0.data/data/share/man/man1/mid3v2.1
mutagen-1.45.0.data/data/share/man/man1/moggsplit.1
mutagen-1.45.0.data/data/share/man/man1/mutagen-inspect.1
mutagen-1.45.0.data/data/share/man/man1/mutagen-pony.1
mutagen-1.45.0.dist-info/COPYING
mutagen-1.45.0.dist-info/METADATA
mutagen-1.45.0.dist-info/WHEEL
mutagen-1.45.0.dist-info/entry_points.txt
mutagen-1.45.0.dist-info/top_level.txt
mutagen-1.45.0.dist-info/RECORD
