Metadata-Version: 1.2
Name: mutagen
Version: 1.45.0
Summary: read and write audio tags for many formats
Home-page: https://github.com/quodlibet/mutagen
Author: Christoph Reiter
Author-email: reiter.christoph@gmail.com
License: GPL-2.0-or-later
Platform: UNKNOWN
Classifier: Operating System :: OS Independent
Classifier: Programming Language :: Python :: 3
Classifier: Programming Language :: Python :: 3.5
Classifier: Programming Language :: Python :: 3.6
Classifier: Programming Language :: Python :: 3.7
Classifier: Programming Language :: Python :: 3.8
Classifier: Programming Language :: Python :: Implementation :: CPython
Classifier: Programming Language :: Python :: Implementation :: PyPy
Classifier: License :: OSI Approved :: GNU General Public License v2 or later (GPLv2+)
Classifier: Topic :: Multimedia :: Sound/Audio
Requires-Python: >=3.5, <4
